{"summaries":[{"symbol":{"__symbol":0,"members":[]},"metadata":{"__symbolic":"class","members":{"clearStorage":[{"__symbolic":"method"}],"setItem":[{"__symbolic":"method"}],"getItem":[{"__symbolic":"method"}],"setEncryptedItem":[{"__symbolic":"method"}],"getDecryptedItem":[{"__symbolic":"method"}]}},"type":{"summaryKind":3,"type":{"reference":{"__symbol":0,"members":[]},"diDeps":[],"lifecycleHooks":[]}}}],"symbols":[{"__symbol":0,"name":"SessionStorageService","filePath":"C:/Users/Alex/Code/txtr.io/src/app/core/services/session-storage.service.d.ts"}]}